pyv/core/__init__.py
pyv/core/auto_versionning.py
pyv/core/utils.py
pyv/core/versionning.py
pyv/main.py
versioning_python-0.1.0.dist-info/METADATA
versioning_python-0.1.0.dist-info/WHEEL
versioning_python-0.1.0.dist-info/entry_points.txt
versioning_python-0.1.0.dist-info/RECORD
