Metadata-Version: 2.1
Name: versioning-python
Version: 0.1.0
Summary: A command-line interface (CLI) application for managing versioning in a using Python
Home-page: https://github.com/Hermann-web/pyv
License: MIT
Author: Hermann Agossou
Maintainer: Hermann Agossou
Maintainer-email: agossouhermann7@gmail.com
Requires-Python: >=3.7,<4.0
Classifier: License :: OSI Approved :: MIT License
Classifier: Programming Language :: Python :: 3
Classifier: Programming Language :: Python :: 3.7
Classifier: Programming Language :: Python :: 3.8
Classifier: Programming Language :: Python :: 3.9
Classifier: Programming Language :: Python :: 3.10
Classifier: Programming Language :: Python :: 3.11
Classifier: Programming Language :: Python :: 3.12
Requires-Dist: gitdb (>=4.0.10,<5.0.0)
Requires-Dist: gitpython (>=3.1.32,<4.0.0)
Requires-Dist: smmap (>=5.0.0,<6.0.0)
Project-URL: Documentation, https://readthedocs.org/projects/pyv/
Project-URL: Repository, https://github.com/Hermann-web/pyv
